{"nodes": [{"id": "c_users_tjmel_onedrive_documents_cursor_proj_autoos_subnet_broker_probe_fluid_lua", "label": "probe_fluid.lua", "file_type": "code", "source_file": "C:\\Users\\tjmel\\OneDrive\\Documents\\Cursor_proj\\AutoOS\\subnet_broker\\probe_fluid.lua", "source_location": "L1"}, {"id": "probe_fluid_proxy_adapter", "label": "proxy_adapter()", "file_type": "code", "source_file": "C:\\Users\\tjmel\\OneDrive\\Documents\\Cursor_proj\\AutoOS\\subnet_broker\\probe_fluid.lua", "source_location": "L34"}, {"id": "probe_fluid_proxy_transposer", "label": "proxy_transposer()", "file_type": "code", "source_file": "C:\\Users\\tjmel\\OneDrive\\Documents\\Cursor_proj\\AutoOS\\subnet_broker\\probe_fluid.lua", "source_location": "L41"}, {"id": "probe_fluid_fluid_rows", "label": "fluid_rows()", "file_type": "code", "source_file": "C:\\Users\\tjmel\\OneDrive\\Documents\\Cursor_proj\\AutoOS\\subnet_broker\\probe_fluid.lua", "source_location": "L48"}, {"id": "probe_fluid_tank_level", "label": "tank_level()", "file_type": "code", "source_file": "C:\\Users\\tjmel\\OneDrive\\Documents\\Cursor_proj\\AutoOS\\subnet_broker\\probe_fluid.lua", "source_location": "L49"}, {"id": "probe_fluid_tank_capacity", "label": "tank_capacity()", "file_type": "code", "source_file": "C:\\Users\\tjmel\\OneDrive\\Documents\\Cursor_proj\\AutoOS\\subnet_broker\\probe_fluid.lua", "source_location": "L50"}, {"id": "probe_fluid_print_side", "label": "print_side()", "file_type": "code", "source_file": "C:\\Users\\tjmel\\OneDrive\\Documents\\Cursor_proj\\AutoOS\\subnet_broker\\probe_fluid.lua", "source_location": "L52"}, {"id": "probe_fluid_find_machine", "label": "find_machine()", "file_type": "code", "source_file": "C:\\Users\\tjmel\\OneDrive\\Documents\\Cursor_proj\\AutoOS\\subnet_broker\\probe_fluid.lua", "source_location": "L68"}, {"id": "probe_fluid_bool_arg", "label": "bool_arg()", "file_type": "code", "source_file": "C:\\Users\\tjmel\\OneDrive\\Documents\\Cursor_proj\\AutoOS\\subnet_broker\\probe_fluid.lua", "source_location": "L76"}, {"id": "probe_fluid_run_lane_probe", "label": "run_lane_probe()", "file_type": "code", "source_file": "C:\\Users\\tjmel\\OneDrive\\Documents\\Cursor_proj\\AutoOS\\subnet_broker\\probe_fluid.lua", "source_location": "L82"}, {"id": "probe_fluid_print_central_side", "label": "print_central_side()", "file_type": "code", "source_file": "C:\\Users\\tjmel\\OneDrive\\Documents\\Cursor_proj\\AutoOS\\subnet_broker\\probe_fluid.lua", "source_location": "L126"}, {"id": "probe_fluid_run_central_probe", "label": "run_central_probe()", "file_type": "code", "source_file": "C:\\Users\\tjmel\\OneDrive\\Documents\\Cursor_proj\\AutoOS\\subnet_broker\\probe_fluid.lua", "source_location": "L131"}], "edges": [{"source": "c_users_tjmel_onedrive_documents_cursor_proj_autoos_subnet_broker_probe_fluid_lua", "target": "config", "relation": "imports", "confidence": "EXTRACTED", "confidence_score": 1.0, "source_file": "C:\\Users\\tjmel\\OneDrive\\Documents\\Cursor_proj\\AutoOS\\subnet_broker\\probe_fluid.lua", "source_location": "29", "weight": 1.0}, {"source": "c_users_tjmel_onedrive_documents_cursor_proj_autoos_subnet_broker_probe_fluid_lua", "target": "lane_sides", "relation": "imports", "confidence": "EXTRACTED", "confidence_score": 1.0, "source_file": "C:\\Users\\tjmel\\OneDrive\\Documents\\Cursor_proj\\AutoOS\\subnet_broker\\probe_fluid.lua", "source_location": "30", "weight": 1.0}, {"source": "c_users_tjmel_onedrive_documents_cursor_proj_autoos_subnet_broker_probe_fluid_lua", "target": "component", "relation": "imports", "confidence": "EXTRACTED", "confidence_score": 1.0, "source_file": "C:\\Users\\tjmel\\OneDrive\\Documents\\Cursor_proj\\AutoOS\\subnet_broker\\probe_fluid.lua", "source_location": "31", "weight": 1.0}, {"source": "c_users_tjmel_onedrive_documents_cursor_proj_autoos_subnet_broker_probe_fluid_lua", "target": "fluid_tanks", "relation": "imports", "confidence": "EXTRACTED", "confidence_score": 1.0, "source_file": "C:\\Users\\tjmel\\OneDrive\\Documents\\Cursor_proj\\AutoOS\\subnet_broker\\probe_fluid.lua", "source_location": "32", "weight": 1.0}, {"source": "c_users_tjmel_onedrive_documents_cursor_proj_autoos_subnet_broker_probe_fluid_lua", "target": "probe_fluid_proxy_adapter", "relation": "contains", "confidence": "EXTRACTED", "source_file": "C:\\Users\\tjmel\\OneDrive\\Documents\\Cursor_proj\\AutoOS\\subnet_broker\\probe_fluid.lua", "source_location": "L34", "weight": 1.0}, {"source": "c_users_tjmel_onedrive_documents_cursor_proj_autoos_subnet_broker_probe_fluid_lua", "target": "probe_fluid_proxy_transposer", "relation": "contains", "confidence": "EXTRACTED", "source_file": "C:\\Users\\tjmel\\OneDrive\\Documents\\Cursor_proj\\AutoOS\\subnet_broker\\probe_fluid.lua", "source_location": "L41", "weight": 1.0}, {"source": "c_users_tjmel_onedrive_documents_cursor_proj_autoos_subnet_broker_probe_fluid_lua", "target": "probe_fluid_fluid_rows", "relation": "contains", "confidence": "EXTRACTED", "source_file": "C:\\Users\\tjmel\\OneDrive\\Documents\\Cursor_proj\\AutoOS\\subnet_broker\\probe_fluid.lua", "source_location": "L48", "weight": 1.0}, {"source": "c_users_tjmel_onedrive_documents_cursor_proj_autoos_subnet_broker_probe_fluid_lua", "target": "probe_fluid_tank_level", "relation": "contains", "confidence": "EXTRACTED", "source_file": "C:\\Users\\tjmel\\OneDrive\\Documents\\Cursor_proj\\AutoOS\\subnet_broker\\probe_fluid.lua", "source_location": "L49", "weight": 1.0}, {"source": "c_users_tjmel_onedrive_documents_cursor_proj_autoos_subnet_broker_probe_fluid_lua", "target": "probe_fluid_tank_capacity", "relation": "contains", "confidence": "EXTRACTED", "source_file": "C:\\Users\\tjmel\\OneDrive\\Documents\\Cursor_proj\\AutoOS\\subnet_broker\\probe_fluid.lua", "source_location": "L50", "weight": 1.0}, {"source": "c_users_tjmel_onedrive_documents_cursor_proj_autoos_subnet_broker_probe_fluid_lua", "target": "probe_fluid_print_side", "relation": "contains", "confidence": "EXTRACTED", "source_file": "C:\\Users\\tjmel\\OneDrive\\Documents\\Cursor_proj\\AutoOS\\subnet_broker\\probe_fluid.lua", "source_location": "L52", "weight": 1.0}, {"source": "c_users_tjmel_onedrive_documents_cursor_proj_autoos_subnet_broker_probe_fluid_lua", "target": "probe_fluid_find_machine", "relation": "contains", "confidence": "EXTRACTED", "source_file": "C:\\Users\\tjmel\\OneDrive\\Documents\\Cursor_proj\\AutoOS\\subnet_broker\\probe_fluid.lua", "source_location": "L68", "weight": 1.0}, {"source": "c_users_tjmel_onedrive_documents_cursor_proj_autoos_subnet_broker_probe_fluid_lua", "target": "probe_fluid_bool_arg", "relation": "contains", "confidence": "EXTRACTED", "source_file": "C:\\Users\\tjmel\\OneDrive\\Documents\\Cursor_proj\\AutoOS\\subnet_broker\\probe_fluid.lua", "source_location": "L76", "weight": 1.0}, {"source": "c_users_tjmel_onedrive_documents_cursor_proj_autoos_subnet_broker_probe_fluid_lua", "target": "probe_fluid_run_lane_probe", "relation": "contains", "confidence": "EXTRACTED", "source_file": "C:\\Users\\tjmel\\OneDrive\\Documents\\Cursor_proj\\AutoOS\\subnet_broker\\probe_fluid.lua", "source_location": "L82", "weight": 1.0}, {"source": "c_users_tjmel_onedrive_documents_cursor_proj_autoos_subnet_broker_probe_fluid_lua", "target": "probe_fluid_print_central_side", "relation": "contains", "confidence": "EXTRACTED", "source_file": "C:\\Users\\tjmel\\OneDrive\\Documents\\Cursor_proj\\AutoOS\\subnet_broker\\probe_fluid.lua", "source_location": "L126", "weight": 1.0}, {"source": "c_users_tjmel_onedrive_documents_cursor_proj_autoos_subnet_broker_probe_fluid_lua", "target": "probe_fluid_run_central_probe", "relation": "contains", "confidence": "EXTRACTED", "source_file": "C:\\Users\\tjmel\\OneDrive\\Documents\\Cursor_proj\\AutoOS\\subnet_broker\\probe_fluid.lua", "source_location": "L131", "weight": 1.0}, {"source": "probe_fluid_print_side", "target": "probe_fluid_tank_level", "relation": "calls", "confidence": "EXTRACTED", "source_file": "C:\\Users\\tjmel\\OneDrive\\Documents\\Cursor_proj\\AutoOS\\subnet_broker\\probe_fluid.lua", "source_location": "L53", "weight": 1.0}, {"source": "probe_fluid_print_side", "target": "probe_fluid_tank_capacity", "relation": "calls", "confidence": "EXTRACTED", "source_file": "C:\\Users\\tjmel\\OneDrive\\Documents\\Cursor_proj\\AutoOS\\subnet_broker\\probe_fluid.lua", "source_location": "L54", "weight": 1.0}, {"source": "probe_fluid_print_side", "target": "probe_fluid_fluid_rows", "relation": "calls", "confidence": "EXTRACTED", "source_file": "C:\\Users\\tjmel\\OneDrive\\Documents\\Cursor_proj\\AutoOS\\subnet_broker\\probe_fluid.lua", "source_location": "L61", "weight": 1.0}, {"source": "probe_fluid_run_lane_probe", "target": "probe_fluid_proxy_transposer", "relation": "calls", "confidence": "EXTRACTED", "source_file": "C:\\Users\\tjmel\\OneDrive\\Documents\\Cursor_proj\\AutoOS\\subnet_broker\\probe_fluid.lua", "source_location": "L86", "weight": 1.0}, {"source": "probe_fluid_run_lane_probe", "target": "probe_fluid_print_side", "relation": "calls", "confidence": "EXTRACTED", "source_file": "C:\\Users\\tjmel\\OneDrive\\Documents\\Cursor_proj\\AutoOS\\subnet_broker\\probe_fluid.lua", "source_location": "L105", "weight": 1.0}, {"source": "probe_fluid_run_lane_probe", "target": "probe_fluid_tank_level", "relation": "calls", "confidence": "EXTRACTED", "source_file": "C:\\Users\\tjmel\\OneDrive\\Documents\\Cursor_proj\\AutoOS\\subnet_broker\\probe_fluid.lua", "source_location": "L113", "weight": 1.0}, {"source": "probe_fluid_print_central_side", "target": "probe_fluid_print_side", "relation": "calls", "confidence": "EXTRACTED", "source_file": "C:\\Users\\tjmel\\OneDrive\\Documents\\Cursor_proj\\AutoOS\\subnet_broker\\probe_fluid.lua", "source_location": "L128", "weight": 1.0}, {"source": "probe_fluid_run_central_probe", "target": "probe_fluid_proxy_adapter", "relation": "calls", "confidence": "EXTRACTED", "source_file": "C:\\Users\\tjmel\\OneDrive\\Documents\\Cursor_proj\\AutoOS\\subnet_broker\\probe_fluid.lua", "source_location": "L142", "weight": 1.0}, {"source": "probe_fluid_run_central_probe", "target": "probe_fluid_print_central_side", "relation": "calls", "confidence": "EXTRACTED", "source_file": "C:\\Users\\tjmel\\OneDrive\\Documents\\Cursor_proj\\AutoOS\\subnet_broker\\probe_fluid.lua", "source_location": "L146", "weight": 1.0}, {"source": "probe_fluid_run_central_probe", "target": "probe_fluid_print_side", "relation": "calls", "confidence": "EXTRACTED", "source_file": "C:\\Users\\tjmel\\OneDrive\\Documents\\Cursor_proj\\AutoOS\\subnet_broker\\probe_fluid.lua", "source_location": "L149", "weight": 1.0}], "raw_calls": [{"caller_nid": "probe_fluid_proxy_adapter", "callee": "pcall", "source_file": "C:\\Users\\tjmel\\OneDrive\\Documents\\Cursor_proj\\AutoOS\\subnet_broker\\probe_fluid.lua", "source_location": "L35"}, {"caller_nid": "probe_fluid_proxy_adapter", "callee": "pcall", "source_file": "C:\\Users\\tjmel\\OneDrive\\Documents\\Cursor_proj\\AutoOS\\subnet_broker\\probe_fluid.lua", "source_location": "L37"}, {"caller_nid": "probe_fluid_proxy_transposer", "callee": "pcall", "source_file": "C:\\Users\\tjmel\\OneDrive\\Documents\\Cursor_proj\\AutoOS\\subnet_broker\\probe_fluid.lua", "source_location": "L42"}, {"caller_nid": "probe_fluid_proxy_transposer", "callee": "pcall", "source_file": "C:\\Users\\tjmel\\OneDrive\\Documents\\Cursor_proj\\AutoOS\\subnet_broker\\probe_fluid.lua", "source_location": "L44"}, {"caller_nid": "probe_fluid_fluid_rows", "callee": "FluidTanks.fluid_rows", "source_file": "C:\\Users\\tjmel\\OneDrive\\Documents\\Cursor_proj\\AutoOS\\subnet_broker\\probe_fluid.lua", "source_location": "L48"}, {"caller_nid": "probe_fluid_tank_level", "callee": "FluidTanks.tank_level", "source_file": "C:\\Users\\tjmel\\OneDrive\\Documents\\Cursor_proj\\AutoOS\\subnet_broker\\probe_fluid.lua", "source_location": "L49"}, {"caller_nid": "probe_fluid_tank_capacity", "callee": "FluidTanks.tank_capacity", "source_file": "C:\\Users\\tjmel\\OneDrive\\Documents\\Cursor_proj\\AutoOS\\subnet_broker\\probe_fluid.lua", "source_location": "L50"}, {"caller_nid": "probe_fluid_print_side", "callee": "tostring", "source_file": "C:\\Users\\tjmel\\OneDrive\\Documents\\Cursor_proj\\AutoOS\\subnet_broker\\probe_fluid.lua", "source_location": "L55"}, {"caller_nid": "probe_fluid_print_side", "callee": "string.format", "source_file": "C:\\Users\\tjmel\\OneDrive\\Documents\\Cursor_proj\\AutoOS\\subnet_broker\\probe_fluid.lua", "source_location": "L56"}, {"caller_nid": "probe_fluid_print_side", "callee": "tostring", "source_file": "C:\\Users\\tjmel\\OneDrive\\Documents\\Cursor_proj\\AutoOS\\subnet_broker\\probe_fluid.lua", "source_location": "L58"}, {"caller_nid": "probe_fluid_print_side", "callee": "print", "source_file": "C:\\Users\\tjmel\\OneDrive\\Documents\\Cursor_proj\\AutoOS\\subnet_broker\\probe_fluid.lua", "source_location": "L60"}, {"caller_nid": "probe_fluid_print_side", "callee": "ipairs", "source_file": "C:\\Users\\tjmel\\OneDrive\\Documents\\Cursor_proj\\AutoOS\\subnet_broker\\probe_fluid.lua", "source_location": "L63"}, {"caller_nid": "probe_fluid_print_side", "callee": "print", "source_file": "C:\\Users\\tjmel\\OneDrive\\Documents\\Cursor_proj\\AutoOS\\subnet_broker\\probe_fluid.lua", "source_location": "L64"}, {"caller_nid": "probe_fluid_print_side", "callee": "string.format", "source_file": "C:\\Users\\tjmel\\OneDrive\\Documents\\Cursor_proj\\AutoOS\\subnet_broker\\probe_fluid.lua", "source_location": "L64"}, {"caller_nid": "probe_fluid_print_side", "callee": "tostring", "source_file": "C:\\Users\\tjmel\\OneDrive\\Documents\\Cursor_proj\\AutoOS\\subnet_broker\\probe_fluid.lua", "source_location": "L64"}, {"caller_nid": "probe_fluid_print_side", "callee": "tostring", "source_file": "C:\\Users\\tjmel\\OneDrive\\Documents\\Cursor_proj\\AutoOS\\subnet_broker\\probe_fluid.lua", "source_location": "L64"}, {"caller_nid": "probe_fluid_find_machine", "callee": "ipairs", "source_file": "C:\\Users\\tjmel\\OneDrive\\Documents\\Cursor_proj\\AutoOS\\subnet_broker\\probe_fluid.lua", "source_location": "L70"}, {"caller_nid": "probe_fluid_bool_arg", "callee": "type", "source_file": "C:\\Users\\tjmel\\OneDrive\\Documents\\Cursor_proj\\AutoOS\\subnet_broker\\probe_fluid.lua", "source_location": "L77"}, {"caller_nid": "probe_fluid_run_lane_probe", "callee": "LaneSides.fluid_transposer_address", "source_file": "C:\\Users\\tjmel\\OneDrive\\Documents\\Cursor_proj\\AutoOS\\subnet_broker\\probe_fluid.lua", "source_location": "L83"}, {"caller_nid": "probe_fluid_run_lane_probe", "callee": "print", "source_file": "C:\\Users\\tjmel\\OneDrive\\Documents\\Cursor_proj\\AutoOS\\subnet_broker\\probe_fluid.lua", "source_location": "L84"}, {"caller_nid": "probe_fluid_run_lane_probe", "callee": "string.rep", "source_file": "C:\\Users\\tjmel\\OneDrive\\Documents\\Cursor_proj\\AutoOS\\subnet_broker\\probe_fluid.lua", "source_location": "L84"}, {"caller_nid": "probe_fluid_run_lane_probe", "callee": "print", "source_file": "C:\\Users\\tjmel\\OneDrive\\Documents\\Cursor_proj\\AutoOS\\subnet_broker\\probe_fluid.lua", "source_location": "L85"}, {"caller_nid": "probe_fluid_run_lane_probe", "callee": "string.format", "source_file": "C:\\Users\\tjmel\\OneDrive\\Documents\\Cursor_proj\\AutoOS\\subnet_broker\\probe_fluid.lua", "source_location": "L85"}, {"caller_nid": "probe_fluid_run_lane_probe", "callee": "tostring", "source_file": "C:\\Users\\tjmel\\OneDrive\\Documents\\Cursor_proj\\AutoOS\\subnet_broker\\probe_fluid.lua", "source_location": "L85"}, {"caller_nid": "probe_fluid_run_lane_probe", "callee": "tostring", "source_file": "C:\\Users\\tjmel\\OneDrive\\Documents\\Cursor_proj\\AutoOS\\subnet_broker\\probe_fluid.lua", "source_location": "L85"}, {"caller_nid": "probe_fluid_run_lane_probe", "callee": "print", "source_file": "C:\\Users\\tjmel\\OneDrive\\Documents\\Cursor_proj\\AutoOS\\subnet_broker\\probe_fluid.lua", "source_location": "L88"}, {"caller_nid": "probe_fluid_run_lane_probe", "callee": "LaneSides.fluid_buffer_side", "source_file": "C:\\Users\\tjmel\\OneDrive\\Documents\\Cursor_proj\\AutoOS\\subnet_broker\\probe_fluid.lua", "source_location": "L92"}, {"caller_nid": "probe_fluid_run_lane_probe", "callee": "LaneSides.fluid_hatch_side", "source_file": "C:\\Users\\tjmel\\OneDrive\\Documents\\Cursor_proj\\AutoOS\\subnet_broker\\probe_fluid.lua", "source_location": "L93"}, {"caller_nid": "probe_fluid_run_lane_probe", "callee": "print", "source_file": "C:\\Users\\tjmel\\OneDrive\\Documents\\Cursor_proj\\AutoOS\\subnet_broker\\probe_fluid.lua", "source_location": "L94"}, {"caller_nid": "probe_fluid_run_lane_probe", "callee": "string.format", "source_file": "C:\\Users\\tjmel\\OneDrive\\Documents\\Cursor_proj\\AutoOS\\subnet_broker\\probe_fluid.lua", "source_location": "L94"}, {"caller_nid": "probe_fluid_run_lane_probe", "callee": "print", "source_file": "C:\\Users\\tjmel\\OneDrive\\Documents\\Cursor_proj\\AutoOS\\subnet_broker\\probe_fluid.lua", "source_location": "L110"}, {"caller_nid": "probe_fluid_run_lane_probe", "callee": "pcall", "source_file": "C:\\Users\\tjmel\\OneDrive\\Documents\\Cursor_proj\\AutoOS\\subnet_broker\\probe_fluid.lua", "source_location": "L115"}, {"caller_nid": "probe_fluid_run_lane_probe", "callee": "print", "source_file": "C:\\Users\\tjmel\\OneDrive\\Documents\\Cursor_proj\\AutoOS\\subnet_broker\\probe_fluid.lua", "source_location": "L118"}, {"caller_nid": "probe_fluid_run_lane_probe", "callee": "string.format", "source_file": "C:\\Users\\tjmel\\OneDrive\\Documents\\Cursor_proj\\AutoOS\\subnet_broker\\probe_fluid.lua", "source_location": "L118"}, {"caller_nid": "probe_fluid_run_lane_probe", "callee": "tostring", "source_file": "C:\\Users\\tjmel\\OneDrive\\Documents\\Cursor_proj\\AutoOS\\subnet_broker\\probe_fluid.lua", "source_location": "L120"}, {"caller_nid": "probe_fluid_run_lane_probe", "callee": "tostring", "source_file": "C:\\Users\\tjmel\\OneDrive\\Documents\\Cursor_proj\\AutoOS\\subnet_broker\\probe_fluid.lua", "source_location": "L120"}, {"caller_nid": "probe_fluid_run_lane_probe", "callee": "tostring", "source_file": "C:\\Users\\tjmel\\OneDrive\\Documents\\Cursor_proj\\AutoOS\\subnet_broker\\probe_fluid.lua", "source_location": "L121"}, {"caller_nid": "probe_fluid_run_lane_probe", "callee": "tostring", "source_file": "C:\\Users\\tjmel\\OneDrive\\Documents\\Cursor_proj\\AutoOS\\subnet_broker\\probe_fluid.lua", "source_location": "L121"}, {"caller_nid": "probe_fluid_run_lane_probe", "callee": "tostring", "source_file": "C:\\Users\\tjmel\\OneDrive\\Documents\\Cursor_proj\\AutoOS\\subnet_broker\\probe_fluid.lua", "source_location": "L122"}, {"caller_nid": "probe_fluid_run_lane_probe", "callee": "tostring", "source_file": "C:\\Users\\tjmel\\OneDrive\\Documents\\Cursor_proj\\AutoOS\\subnet_broker\\probe_fluid.lua", "source_location": "L122"}, {"caller_nid": "probe_fluid_run_central_probe", "callee": "type", "source_file": "C:\\Users\\tjmel\\OneDrive\\Documents\\Cursor_proj\\AutoOS\\subnet_broker\\probe_fluid.lua", "source_location": "L132"}, {"caller_nid": "probe_fluid_run_central_probe", "callee": "print", "source_file": "C:\\Users\\tjmel\\OneDrive\\Documents\\Cursor_proj\\AutoOS\\subnet_broker\\probe_fluid.lua", "source_location": "L134"}, {"caller_nid": "probe_fluid_run_central_probe", "callee": "string.rep", "source_file": "C:\\Users\\tjmel\\OneDrive\\Documents\\Cursor_proj\\AutoOS\\subnet_broker\\probe_fluid.lua", "source_location": "L134"}, {"caller_nid": "probe_fluid_run_central_probe", "callee": "print", "source_file": "C:\\Users\\tjmel\\OneDrive\\Documents\\Cursor_proj\\AutoOS\\subnet_broker\\probe_fluid.lua", "source_location": "L135"}, {"caller_nid": "probe_fluid_run_central_probe", "callee": "print", "source_file": "C:\\Users\\tjmel\\OneDrive\\Documents\\Cursor_proj\\AutoOS\\subnet_broker\\probe_fluid.lua", "source_location": "L138"}, {"caller_nid": "probe_fluid_run_central_probe", "callee": "string.format", "source_file": "C:\\Users\\tjmel\\OneDrive\\Documents\\Cursor_proj\\AutoOS\\subnet_broker\\probe_fluid.lua", "source_location": "L138"}, {"caller_nid": "probe_fluid_run_central_probe", "callee": "tostring", "source_file": "C:\\Users\\tjmel\\OneDrive\\Documents\\Cursor_proj\\AutoOS\\subnet_broker\\probe_fluid.lua", "source_location": "L140"}, {"caller_nid": "probe_fluid_run_central_probe", "callee": "tostring", "source_file": "C:\\Users\\tjmel\\OneDrive\\Documents\\Cursor_proj\\AutoOS\\subnet_broker\\probe_fluid.lua", "source_location": "L140"}, {"caller_nid": "probe_fluid_run_central_probe", "callee": "print", "source_file": "C:\\Users\\tjmel\\OneDrive\\Documents\\Cursor_proj\\AutoOS\\subnet_broker\\probe_fluid.lua", "source_location": "L144"}, {"caller_nid": "probe_fluid_run_central_probe", "callee": "type", "source_file": "C:\\Users\\tjmel\\OneDrive\\Documents\\Cursor_proj\\AutoOS\\subnet_broker\\probe_fluid.lua", "source_location": "L145"}, {"caller_nid": "probe_fluid_run_central_probe", "callee": "print", "source_file": "C:\\Users\\tjmel\\OneDrive\\Documents\\Cursor_proj\\AutoOS\\subnet_broker\\probe_fluid.lua", "source_location": "L148"}, {"caller_nid": "probe_fluid_run_central_probe", "callee": "print", "source_file": "C:\\Users\\tjmel\\OneDrive\\Documents\\Cursor_proj\\AutoOS\\subnet_broker\\probe_fluid.lua", "source_location": "L152"}, {"caller_nid": "probe_fluid_run_central_probe", "callee": "print", "source_file": "C:\\Users\\tjmel\\OneDrive\\Documents\\Cursor_proj\\AutoOS\\subnet_broker\\probe_fluid.lua", "source_location": "L156"}, {"caller_nid": "probe_fluid_run_central_probe", "callee": "string.format", "source_file": "C:\\Users\\tjmel\\OneDrive\\Documents\\Cursor_proj\\AutoOS\\subnet_broker\\probe_fluid.lua", "source_location": "L156"}, {"caller_nid": "probe_fluid_run_central_probe", "callee": "tostring", "source_file": "C:\\Users\\tjmel\\OneDrive\\Documents\\Cursor_proj\\AutoOS\\subnet_broker\\probe_fluid.lua", "source_location": "L158"}, {"caller_nid": "probe_fluid_run_central_probe", "callee": "tostring", "source_file": "C:\\Users\\tjmel\\OneDrive\\Documents\\Cursor_proj\\AutoOS\\subnet_broker\\probe_fluid.lua", "source_location": "L158"}, {"caller_nid": "probe_fluid_run_central_probe", "callee": "print", "source_file": "C:\\Users\\tjmel\\OneDrive\\Documents\\Cursor_proj\\AutoOS\\subnet_broker\\probe_fluid.lua", "source_location": "L162"}, {"caller_nid": "probe_fluid_run_central_probe", "callee": "type", "source_file": "C:\\Users\\tjmel\\OneDrive\\Documents\\Cursor_proj\\AutoOS\\subnet_broker\\probe_fluid.lua", "source_location": "L163"}, {"caller_nid": "probe_fluid_run_central_probe", "callee": "print", "source_file": "C:\\Users\\tjmel\\OneDrive\\Documents\\Cursor_proj\\AutoOS\\subnet_broker\\probe_fluid.lua", "source_location": "L166"}, {"caller_nid": "probe_fluid_run_central_probe", "callee": "print", "source_file": "C:\\Users\\tjmel\\OneDrive\\Documents\\Cursor_proj\\AutoOS\\subnet_broker\\probe_fluid.lua", "source_location": "L170"}]}