{"nodes": [{"id": "c_users_tjmel_onedrive_documents_cursor_proj_autoos_subnet_broker_broker_poll_cache_lua", "label": "broker_poll_cache.lua", "file_type": "code", "source_file": "C:\\Users\\tjmel\\OneDrive\\Documents\\Cursor_proj\\AutoOS\\subnet_broker\\broker_poll_cache.lua", "source_location": "L1"}, {"id": "broker_poll_cache_pollcache_write", "label": "PollCache.write()", "file_type": "code", "source_file": "C:\\Users\\tjmel\\OneDrive\\Documents\\Cursor_proj\\AutoOS\\subnet_broker\\broker_poll_cache.lua", "source_location": "L8"}, {"id": "broker_poll_cache_pollcache_mark_dirty", "label": "PollCache.mark_dirty()", "file_type": "code", "source_file": "C:\\Users\\tjmel\\OneDrive\\Documents\\Cursor_proj\\AutoOS\\subnet_broker\\broker_poll_cache.lua", "source_location": "L13"}], "edges": [{"source": "c_users_tjmel_onedrive_documents_cursor_proj_autoos_subnet_broker_broker_poll_cache_lua", "target": "broker_poll_cache_pollcache_write", "relation": "contains", "confidence": "EXTRACTED", "source_file": "C:\\Users\\tjmel\\OneDrive\\Documents\\Cursor_proj\\AutoOS\\subnet_broker\\broker_poll_cache.lua", "source_location": "L8", "weight": 1.0}, {"source": "c_users_tjmel_onedrive_documents_cursor_proj_autoos_subnet_broker_broker_poll_cache_lua", "target": "broker_poll_cache_pollcache_mark_dirty", "relation": "contains", "confidence": "EXTRACTED", "source_file": "C:\\Users\\tjmel\\OneDrive\\Documents\\Cursor_proj\\AutoOS\\subnet_broker\\broker_poll_cache.lua", "source_location": "L13", "weight": 1.0}], "raw_calls": []}